docker_compose_diagram/__init__.py
docker_compose_diagram/cli.py
docker_compose_diagram/constants.py
docker_compose_diagram/di_container/__init__.py
docker_compose_diagram/di_container/facade.py
docker_compose_diagram/di_container/terminal.py
docker_compose_diagram/docker_compose/__init__.py
docker_compose_diagram/docker_compose/constants/__init__.py
docker_compose_diagram/docker_compose/constants/labels.py
docker_compose_diagram/docker_compose/constants/messages.py
docker_compose_diagram/docker_compose/entities/__init__.py
docker_compose_diagram/docker_compose/entities/service.py
docker_compose_diagram/docker_compose/file_reader/__init__.py
docker_compose_diagram/docker_compose/file_reader/base.py
docker_compose_diagram/docker_compose/file_reader/standard.py
docker_compose_diagram/docker_compose/parser/__init__.py
docker_compose_diagram/docker_compose/parser/base.py
docker_compose_diagram/docker_compose/parser/yaml.py
docker_compose_diagram/docker_images/__init__.py
docker_compose_diagram/docker_images/diagrams_nodes_importer.py
docker_compose_diagram/docker_images/patterns.py
docker_compose_diagram/docker_images/utils.py
docker_compose_diagram/facade.py
docker_compose_diagram/renderer/__init__.py
docker_compose_diagram/renderer/base.py
docker_compose_diagram/renderer/constants/__init__.py
docker_compose_diagram/renderer/constants/messages.py
docker_compose_diagram/renderer/diagrams.py
docker_compose_diagram/renderer/plugins/__init__.py
docker_compose_diagram/renderer/plugins/base.py
docker_compose_diagram/renderer/plugins/diagrams.py
docker_compose_diagram/terminal/__init__.py
docker_compose_diagram/terminal/base.py
docker_compose_diagram/terminal/rich_terminal.py
docker_compose_diagram-0.6.0.dist-info/LICENSE.md
docker_compose_diagram-0.6.0.dist-info/METADATA
docker_compose_diagram-0.6.0.dist-info/WHEEL
docker_compose_diagram-0.6.0.dist-info/entry_points.txt
docker_compose_diagram-0.6.0.dist-info/RECORD
